parxel/__init__.py
parxel/iterator.py
parxel/lexer.py
parxel/nodes.py
parxel/parser.py
parxel/token.py
parxel-0.0.21.dist-info/licenses/LICENSE
parxel-0.0.21.dist-info/METADATA
parxel-0.0.21.dist-info/WHEEL
parxel-0.0.21.dist-info/top_level.txt
parxel-0.0.21.dist-info/RECORD
