Metadata-Version: 2.4
Name: parxel
Version: 0.0.21
Summary: A small lexer and parser utility library
Author: styinx
License: MIT License
Project-URL: Homepage, https://github.com/styinx/ParxeL
Project-URL: Issues, https://github.com/styinx/ParxeL/issues
Classifier: Development Status :: 3 - Alpha
Classifier: Intended Audience :: Developers
Classifier: Operating System :: OS Independent
Classifier: Programming Language :: Python :: 3.11
Classifier: Topic :: Text Processing
Classifier: Topic :: Utilities
Requires-Python: >=3.11
License-File: LICENSE
Dynamic: license-file
